Workbook
Name a: #REF!
Name d: #REF!
Name Database2: #REF!
Name dwa: #REF!
Name IQ_CH: 110000
Name IQ_CQ: 5000
Name IQ_CY: 10000
Name IQ_DAILY: 500000
Name IQ_FH: 100000
Name IQ_FQ: 500
Name IQ_FY: 1000
Name IQ_LTM: 2000
Name IQ_MONTH: 15000
Name IQ_NTM: 6000
Name IQ_WEEK: 50000
Name IQ_YTD: 3000
Name Mining: #REF!
Name qryProjectSearch2: #REF!
Name qryProjectsSearch: #REF!
Name SearchFieldsMajorProjectsInventory: #REF!
Name SearchFieldsMajorProjectsInventory2: #REF!
Name Status: #REF!
Name Status_Change: #REF!

Sheet mpi_dataset_summary_2017-2024
A1: Unique ID | B1: company | C1: project | D1: province | E1: company_type | F1: start_year | G1: end_year | H1: reporting_years | I1: start_status | J1: end_status | K1: current_survival | L1: end_success | M1: project_cost | N1: cost_percentile | O1: latitude_1 | P1: longitude_1 | Q1: sector | R1: group | S1: cleantech | T1: abbreviation
A2: 0 | B2: Bighorn Mining, LTD | C2: Vista Coal Project (Expansion Projects) | D2: AB | E2: Private | F2: 2018 | G2: 2024 | H2: ='mpi_dataset_summary_2017-2024'!$G2-'mpi_dataset_summary_2017-2024'!$F2+1 -> 7 | I2: Announced & Planning | J2: In Review | K2: =IF('mpi_dataset_summary_2017-2024'!$G2=2024,1,0) -> 1 | L2: =IF(J2="Under Construction",1,0) -> 0 | M2: 870 | N2: =_xlfn.PERCENTRANK.INC($M$2:$M$4056,M2) -> 0.789 | O2: 53.33 | P2: -117.53 | Q2: Mining | R2: Coal | S2: No | T2: MIN-COAL
A3: 1 | B3: Premier Renewable Energy | C3: Nicomen Wind Energy Project | D3: BC | E3: Private | F3: 2017 | G3: 2019 | H3: ='mpi_dataset_summary_2017-2024'!$G3-'mpi_dataset_summary_2017-2024'!$F3+1 -> 3 | I3: In Review | J3: In Review | K3: =IF('mpi_dataset_summary_2017-2024'!$G3=2024,1,0) -> 0 | L3: =IF(J3="Under Construction",1,0) -> 0 | M3: 188 | N3: =_xlfn.PERCENTRANK.INC($M$2:$M$4056,M3) -> 0.48 | O3: 50.212613 | P3: -121.38177 | Q3: Energy | R3: Clean Electricity | S3: Yes | T3: EN-CLEL
A4: 2 | B4: 0887572 B.C. Ltd. | C4: Campbell River Power Enterprises | D4: BC | E4: Private | F4: 2017 | G4: 2023 | H4: ='mpi_dataset_summary_2017-2024'!$G4-'mpi_dataset_summary_2017-2024'!$F4+1 -> 7 | I4: Announced & Planning | J4: Announced & Planning | K4: =IF('mpi_dataset_summary_2017-2024'!$G4=2024,1,0) -> 0 | L4: =IF(J4="Under Construction",1,0) -> 0 | M4: 105 | N4: =_xlfn.PERCENTRANK.INC($M$2:$M$4056,M4) -> 0.363 | O4: 50.750359 | P4: -124.88205 | Q4: Energy | R4: Waste Biomass | S4: Yes | T4: EN-BIO
A5: 3 | B5: KGHM Ajax Mining inc. | C5: Ajax Copper-Gold Mine | D5: BC | E5: Private | F5: 2017 | G5: 2017 | H5: ='mpi_dataset_summary_2017-2024'!$G5-'mpi_dataset_summary_2017-2024'!$F5+1 -> 1 | I5: In Review | J5: In Review | K5: =IF('mpi_dataset_summary_2017-2024'!$G5=2024,1,0) -> 0 | L5: =IF(J5="Under Construction",1,0) -> 0 | M5: 1863 | N5: =_xlfn.PERCENTRANK.INC($M$2:$M$4056,M5) -> 0.889 | O5: 50.599801 | P5: -120.44174 | Q5: Mining | R5: Precious Metal | S5: No | T5: MIN-PM
A6: 10 | B6: Aeolis Wind Power Corporation | C6: Hackney Hills Wind Park | D6: BC | E6: Private | F6: 2017 | G6: 2024 | H6: ='mpi_dataset_summary_2017-2024'!$G6-'mpi_dataset_summary_2017-2024'!$F6+1 -> 8 | I6: In Review | J6: In Review | K6: =IF('mpi_dataset_summary_2017-2024'!$G6=2024,1,0) -> 1 | L6: =IF(J6="Under Construction",1,0) -> 0 | M6: 850 | N6: =_xlfn.PERCENTRANK.INC($M$2:$M$4056,M6) -> 0.787 | O6: 56.249263 | P6: -120.84755 | Q6: Energy | R6: Clean Electricity | S6: Yes | T6: EN-CLEL
A7: 11 | B7: Agnico-Eagle Mines Limited | C7: Meliadine | D7: NU | E7: Private | F7: 2017 | G7: 2018 | H7: ='mpi_dataset_summary_2017-2024'!$G7-'mpi_dataset_summary_2017-2024'!$F7+1 -> 2 | I7: Under Construction | J7: Under Construction | K7: =IF('mpi_dataset_summary_2017-2024'!$G7=2024,1,0) -> 0 | L7: =IF(J7="Under Construction",1,0) -> 1 | M7: 1200 | N7: =_xlfn.PERCENTRANK.INC($M$2:$M$4056,M7) -> 0.829 | O7: 63.025 | P7: -92.215 | Q7: Mining | R7: Precious Metal | S7: No | T7: MIN-PM
A8: 19 | B8: Alberta Wind Energy Corp./Mainstream Renewable Power | C8: Windy Point Wind Farm | D8: AB | E8: Private | F8: 2017 | G8: 2020 | H8: ='mpi_dataset_summary_2017-2024'!$G8-'mpi_dataset_summary_2017-2024'!$F8+1 -> 4 | I8: Announced & Planning | J8: Announced & Planning | K8: =IF('mpi_dataset_summary_2017-2024'!$G8=2024,1,0) -> 0 | L8: =IF(J8="Under Construction",1,0) -> 0 | M8: 150 | N8: =_xlfn.PERCENTRANK.INC($M$2:$M$4056,M8) -> 0.442 | O8: 49.485078 | P8: -113.94403 | Q8: Energy | R8: Clean Electricity | S8: Yes | T8: EN-CLEL
A9: 21 | B9: Champion Iron Limited | C9: Kamistiatusset (Kami) | D9: NL | E9: Private | F9: 2017 | G9: 2024 | H9: ='mpi_dataset_summary_2017-2024'!$G9-'mpi_dataset_summary_2017-2024'!$F9+1 -> 8 | I9: Approved | J9: In Review | K9: =IF('mpi_dataset_summary_2017-2024'!$G9=2024,1,0) -> 1 | L9: =IF(J9="Under Construction",1,0) -> 0 | M9: 3864 | N9: =_xlfn.PERCENTRANK.INC($M$2:$M$4056,M9) -> 0.936 | O9: 52.824 | P9: -67.027 | Q9: Mining | R9: Base Metal | S9: No | T9: MIN-BM
A10: 22 | B10: Kinross Gold Corp. (formerly Rockcliff Metals Corp.) | C10: Snow Lake | D10: MB | E10: Private | F10: 2021 | G10: 2024 | H10: ='mpi_dataset_summary_2017-2024'!$G10-'mpi_dataset_summary_2017-2024'!$F10+1 -> 4 | I10: Announced & Planning | J10: Announced & Planning | K10: =IF('mpi_dataset_summary_2017-2024'!$G10=2024,1,0) -> 1 | L10: =IF(J10="Under Construction",1,0) -> 0 | M10: 96.1 | N10: =_xlfn.PERCENTRANK.INC($M$2:$M$4056,M10) -> 0.34 | O10: 54.91 | P10: -100.031 | Q10: Mining | R10: Critical Mineral | S10: Yes | T10: MIN-CM
A11: 26 | B11: Alouette | C11: Expansion d'usine (aluminium) | D11: QC | E11: Private | F11: 2017 | G11: 2021 | H11: ='mpi_dataset_summary_2017-2024'!$G11-'mpi_dataset_summary_2017-2024'!$F11+1 -> 5 | I11: Announced & Planning | J11: Under Construction | K11: =IF('mpi_dataset_summary_2017-2024'!$G11=2024,1,0) -> 0 | L11: =IF(J11="Under Construction",1,0) -> 1 | M11: 2000 | N11: =_xlfn.PERCENTRANK.INC($M$2:$M$4056,M11) -> 0.894 | O11: 50.209428 | P11: -66.382828 | Q11: Mining | R11: Base Metal | S11: No | T11: MIN-BM
A12: 27 | B12: Alta Energy Corp. | C12: Lower Wood River Hydropower Project | D12: BC | E12: Private | F12: 2017 | G12: 2023 | H12: ='mpi_dataset_summary_2017-2024'!$G12-'mpi_dataset_summary_2017-2024'!$F12+1 -> 7 | I12: Announced & Planning | J12: In Review | K12: =IF('mpi_dataset_summary_2017-2024'!$G12=2024,1,0) -> 0 | L12: =IF(J12="Under Construction",1,0) -> 0 | M12: 144 | N12: =_xlfn.PERCENTRANK.INC($M$2:$M$4056,M12) -> 0.435 | O12: 52.008661 | P12: -118.56377 | Q12: Energy | R12: Clean Electricity | S12: Yes | T12: EN-CLEL
A13: 29 | B13: AltaLink | C13: Southern Alberta Transmission Reinforcement | D13: AB | E13: Private | F13: 2017 | G13: 2018 | H13: ='mpi_dataset_summary_2017-2024'!$G13-'mpi_dataset_summary_2017-2024'!$F13+1 -> 2 | I13: Under Construction | J13: Under Construction | K13: =IF('mpi_dataset_summary_2017-2024'!$G13=2024,1,0) -> 0 | L13: =IF(J13="Under Construction",1,0) -> 1 | M13: 1866 | N13: =_xlfn.PERCENTRANK.INC($M$2:$M$4056,M13) -> 0.89 | O13: 49.724368 | P13: -113.39988 | Q13: Energy | R13: Trans & Distr | S13: No | T13: EN-T&D
... A106: 318 | B106: Northeast Utilities, NSTAR, Hydro-Quebec | C106: Transmission Line - Champlain Hudson Power Express | D106: QC | E106: Public | F106: 2017 | G106: 2017 | H106: ='mpi_dataset_summary_2017-2024'!$G106-'mpi_dataset_summary_2017-2024'!$F106+1 -> 1 | I106: In Review | J106: In Review | K106: =IF('mpi_dataset_summary_2017-2024'!$G106=2024,1,0) -> 0 | L106: =IF(J106="Under Construction",1,0) -> 0 | M106: 400 | N106: =_xlfn.PERCENTRANK.INC($M$2:$M$4056,M106) -> 0.635 | O106: 45.56839 | P106: -71.999691 | Q106: Energy | R106: Trans & Distr | S106: No | T106: EN-T&D
A107: 328 | B107: Numerous Companies | C107: COMFIT Program - Wind Energy | D107: NS | E107: Private | F107: 2017 | G107: 2017 | H107: ='mpi_dataset_summary_2017-2024'!$G107-'mpi_dataset_summary_2017-2024'!$F107+1 -> 1 | I107: Under Construction | J107: Under Construction | K107: =IF('mpi_dataset_summary_2017-2024'!$G107=2024,1,0) -> 0 | L107: =IF(J107="Under Construction",1,0) -> 1 | M107: 330 | N107: =_xlfn.PERCENTRANK.INC($M$2:$M$4056,M107) -> 0.595 | Q107: Energy | R107: Clean Electricity | S107: Yes | T107: EN-CLEL
A108: 329 | B108: Northcliff Resources (HDI Mining) | C108: Sisson Project | D108: NB | E108: Private | F108: 2017 | G108: 2024 | H108: ='mpi_dataset_summary_2017-2024'!$G108-'mpi_dataset_summary_2017-2024'!$F108+1 -> 8 | I108: In Review | J108: Approved | K108: =IF('mpi_dataset_summary_2017-2024'!$G108=2024,1,0) -> 1 | L108: =IF(J108="Under Construction",1,0) -> 0 | M108: 579 | N108: =_xlfn.PERCENTRANK.INC($M$2:$M$4056,M108) -> 0.708 | O108: 46.365 | P108: -67.045 | Q108: Mining | R108: Other | S108: No | T108: MIN-OTH
A109: 333 | B109: Ontario Power Generation | C109: Darlington Refurbishment Project | D109: ON | E109: Public | F109: 2017 | G109: 2024 | H109: ='mpi_dataset_summary_2017-2024'!$G109-'mpi_dataset_summary_2017-2024'!$F109+1 -> 8 | I109: Under Construction | J109: Under Construction | K109: =IF('mpi_dataset_summary_2017-2024'!$G109=2024,1,0) -> 1 | L109: =IF(J109="Under Construction",1,0) -> 1 | M109: 12800 | N109: =_xlfn.PERCENTRANK.INC($M$2:$M$4056,M109) -> 0.984 | O109: 43.869869 | P109: -78.719487 | Q109: Energy | R109: Clean Electricity | S109: Yes | T109: EN-LCF
A110: 334 | B110: Ontario Power Generation | C110: The Deep Geologic Repository Project | D110: ON | E110: Public | F110: 2017 | G110: 2019 | H110: ='mpi_dataset_summary_2017-2024'!$G110-'mpi_dataset_summary_2017-2024'!$F110+1 -> 3 | I110: In Review | J110: In Review | K110: =IF('mpi_dataset_summary_2017-2024'!$G110=2024,1,0) -> 0 | L110: =IF(J110="Under Construction",1,0) -> 0 | M110: 2400 | N110: =_xlfn.PERCENTRANK.INC($M$2:$M$4056,M110) -> 0.908 | O110: 44.178018 | P110: -81.63634 | Q110: Energy | R110: Clean Electricity | S110: Yes | T110: EN-LCF
A111: 340 | B111: Oceanic Iron Ore Company | C111: Hopes Advance Iron Mine (Ungava Bay) | D111: QC | E111: Private | F111: 2020 | G111: 2022 | H111: ='mpi_dataset_summary_2017-2024'!$G111-'mpi_dataset_summary_2017-2024'!$F111+1 -> 3 | I111: In Review | J111: Announced & Planning | K111: =IF('mpi_dataset_summary_2017-2024'!$G111=2024,1,0) -> 0 | L111: =IF(J111="Under Construction",1,0) -> 0 | M111: 1566.612 | N111: =_xlfn.PERCENTRANK.INC($M$2:$M$4056,M111) -> 0.871 | O111: 59.310061 | P111: -69.888941 | Q111: Mining | R111: Base Metal | S111: No | T111: MIN-BM
A112: 341 | B112: Osum Oil Sands Corp. | C112: Taiga | D112: AB | E112: Private | F112: 2017 | G112: 2024 | H112: ='mpi_dataset_summary_2017-2024'!$G112-'mpi_dataset_summary_2017-2024'!$F112+1 -> 8 | I112: Approved | J112: Approved | K112: =IF('mpi_dataset_summary_2017-2024'!$G112=2024,1,0) -> 1 | L112: =IF(J112="Under Construction",1,0) -> 0 | M112: 1570 | N112: =_xlfn.PERCENTRANK.INC($M$2:$M$4056,M112) -> 0.872 | O112: 54.680878 | P112: -110.13648 | Q112: Energy | R112: Oil & Gas - Upstream | S112: No | T112: EN-OG-U
A113: 344 | B113: Agnico Eagle Mines Limited | C113: Hammond Reef | D113: ON | E113: Private | F113: 2021 | G113: 2024 | H113: ='mpi_dataset_summary_2017-2024'!$G113-'mpi_dataset_summary_2017-2024'!$F113+1 -> 4 | I113: In Review | J113: Approved | K113: =IF('mpi_dataset_summary_2017-2024'!$G113=2024,1,0) -> 1 | L113: =IF(J113="Under Construction",1,0) -> 0 | M113: 1300 | N113: =_xlfn.PERCENTRANK.INC($M$2:$M$4056,M113) -> 0.843 | O113: 48.88278 | P113: -91.349945 | Q113: Mining | R113: Other | S113: No | T113: MIN-OTH
A114: 345 | B114: Greengen Holdings Ltd | C114: Bremner Creek Hydro Project | D114: BC | E114: Private | F114: 2017 | G114: 2022 | H114: ='mpi_dataset_summary_2017-2024'!$G114-'mpi_dataset_summary_2017-2024'!$F114+1 -> 6 | I114: In Review | J114: Under Construction | K114: =IF('mpi_dataset_summary_2017-2024'!$G114=2024,1,0) -> 0 | L114: =IF(J114="Under Construction",1,0) -> 1 | M114: 230 | N114: =_xlfn.PERCENTRANK.INC($M$2:$M$4056,M114) -> 0.524 | O114: 49.301789 | P114: -121.78959 | Q114: Energy | R114: Clean Electricity | S114: Yes | T114: EN-CLEL
A115: 346 | B115: Woodside, Chevron (Kitimat LNG) | C115: Pacific Trail Pipeline | D115: BC | E115: Private | F115: 2017 | G115: 2021 | H115: ='mpi_dataset_summary_2017-2024'!$G115-'mpi_dataset_summary_2017-2024'!$F115+1 -> 5 | I115: Approved | J115: Approved | K115: =IF('mpi_dataset_summary_2017-2024'!$G115=2024,1,0) -> 0 | L115: =IF(J115="Under Construction",1,0) -> 0 | M115: 1300 | N115: =_xlfn.PERCENTRANK.INC($M$2:$M$4056,M115) -> 0.843 | O115: 54.262315 | P115: -122.62753 | Q115: Energy | R115: Trans & Distr | S115: No | T115: EN-T&D
A116: 347 | B116: Pacific Booker Minerals Inc. | C116: Morrison Copper Gold Project | D116: BC | E116: Private | F116: 2020 | G116: 2020 | H116: ='mpi_dataset_summary_2017-2024'!$G116-'mpi_dataset_summary_2017-2024'!$F116+1 -> 1 | I116: In Review | J116: In Review | K116: =IF('mpi_dataset_summary_2017-2024'!$G116=2024,1,0) -> 0 | L116: =IF(J116="Under Construction",1,0) -> 0 | M116: 517 | N116: =_xlfn.PERCENTRANK.INC($M$2:$M$4056,M116) -> 0.694 | O116: 55.194 | P116: -126.314 | Q116: Mining | R116: Precious Metal | S116: No | T116: MIN-PM
A117: 352 | B117: Brion Energy Corporation (Petro China) | C117: Thickwood/MacKay River | D117: AB | E117: Private | F117: 2017 | G117: 2017 | H117: ='mpi_dataset_summary_2017-2024'!$G117-'mpi_dataset_summary_2017-2024'!$F117+1 -> 1 | I117: Under Construction | J117: Under Construction | K117: =IF('mpi_dataset_summary_2017-2024'!$G117=2024,1,0) -> 0 | L117: =IF(J117="Under Construction",1,0) -> 1 | M117: 4558 | N117: =_xlfn.PERCENTRANK.INC($M$2:$M$4056,M117) -> 0.944 | O117: 56.813402 | P117: -112.15868 | Q117: Energy | R117: Waste Biomass | S117: Yes | T117: EN-BIO
A118: 360 | B118: Polaris Minerals Corp. | C118: Eagle Rock Quarry | D118: BC | E118: Private | F118: 2017 | G118: 2018 | H118: ='mpi_dataset_summary_2017-2024'!$G118-'mpi_dataset_summary_2017-2024'!$F118+1 -> 2 | I118: Announced & Planning | J118: Announced & Planning | K118: =IF('mpi_dataset_summary_2017-2024'!$G118=2024,1,0) -> 0 | L118: =IF(J118="Under Construction",1,0) -> 0 | M118: 115 | N118: =_xlfn.PERCENTRANK.INC($M$2:$M$4056,M118) -> 0.381 | O118: 49.138597 | P118: -124.78271 | Q118: Mining | R118: Other | S118: No | T118: MIN-OTH
A119: 362 | B119: Potash Corporation of Saskatwchewan | C119: Potash Mine Expansion | D119: SK | E119: Private | F119: 2017 | G119: 2017 | H119: ='mpi_dataset_summary_2017-2024'!$G119-'mpi_dataset_summary_2017-2024'!$F119+1 -> 1 | I119: Under Construction | J119: Under Construction | K119: =IF('mpi_dataset_summary_2017-2024'!$G119=2024,1,0) -> 0 | L119: =IF(J119="Under Construction",1,0) -> 1 | M119: 2800 | N119: =_xlfn.PERCENTRANK.INC($M$2:$M$4056,M119) -> 0.918 | O119: 50.471845 | P119: -101.54355 | Q119: Mining | R119: Precious Metal | S119: No | T119: MIN-PM
... A163: 473 | B163: Value Creation Inc. | C163: Tristar' SAGD Pilot Project | D163: AB | E163: Private | F163: 2020 | G163: 2022 | H163: ='mpi_dataset_summary_2017-2024'!$G163-'mpi_dataset_summary_2017-2024'!$F163+1 -> 3 | I163: In Review | J163: In Review | K163: =IF('mpi_dataset_summary_2017-2024'!$G163=2024,1,0) -> 0 | L163: =IF(J163="Under Construction",1,0) -> 0 | M163: 0 | N163: =_xlfn.PERCENTRANK.INC($M$2:$M$4056,M163) -> 0 | O163: 56.571589 | P163: -111.22844 | Q163: Energy | R163: Oil & Gas - Upstream | S163: No | T163: EN-OG-U
A164: 474 | B164: Various project proponents | C164: Local small scale community and First Nations renewable energy projects | D164: NB | E164: Private | F164: 2017 | G164: 2017 | H164: ='mpi_dataset_summary_2017-2024'!$G164-'mpi_dataset_summary_2017-2024'!$F164+1 -> 1 | I164: Under Construction | J164: Under Construction | K164: =IF('mpi_dataset_summary_2017-2024'!$G164=2024,1,0) -> 0 | L164: =IF(J164="Under Construction",1,0) -> 1 | M164: 250 | N164: =_xlfn.PERCENTRANK.INC($M$2:$M$4056,M164) -> 0.535 | Q164: Energy | R164: Clean Electricity | S164: Yes | T164: EN-CLEL
A165: 477 | B165: Victoria Gold Corporation | C165: Dublin Gulch (Eagle Gold) | D165: YK | E165: Private | F165: 2017 | G165: 2020 | H165: ='mpi_dataset_summary_2017-2024'!$G165-'mpi_dataset_summary_2017-2024'!$F165+1 -> 4 | I165: Approved | J165: Under Construction | K165: =IF('mpi_dataset_summary_2017-2024'!$G165=2024,1,0) -> 0 | L165: =IF(J165="Under Construction",1,0) -> 1 | M165: 487 | N165: =_xlfn.PERCENTRANK.INC($M$2:$M$4056,M165) -> 0.676 | O165: 64.02 | P165: -135.818 | Q165: Mining | R165: Precious Metal | S165: No | T165: MIN-PM
A166: 478 | B166: Victory Nickel | C166: Minago | D166: MB | E166: Private | F166: 2017 | G166: 2017 | H166: ='mpi_dataset_summary_2017-2024'!$G166-'mpi_dataset_summary_2017-2024'!$F166+1 -> 1 | I166: Announced & Planning | J166: Announced & Planning | K166: =IF('mpi_dataset_summary_2017-2024'!$G166=2024,1,0) -> 0 | L166: =IF(J166="Under Construction",1,0) -> 0 | M166: 558 | N166: =_xlfn.PERCENTRANK.INC($M$2:$M$4056,M166) -> 0.704 | O166: 54.09 | P166: -99.193 | Q166: Mining | R166: Critical Mineral | S166: Yes | T166: MIN-CM
A167: 481 | B167: Fort St. James Green Energy Limited Partnership | C167: Fort St-James Green Energy Project | D167: BC | E167: Private | F167: 2017 | G167: 2018 | H167: ='mpi_dataset_summary_2017-2024'!$G167-'mpi_dataset_summary_2017-2024'!$F167+1 -> 2 | I167: Under Construction | J167: Under Construction | K167: =IF('mpi_dataset_summary_2017-2024'!$G167=2024,1,0) -> 0 | L167: =IF(J167="Under Construction",1,0) -> 1 | M167: 235 | N167: =_xlfn.PERCENTRANK.INC($M$2:$M$4056,M167) -> 0.527 | O167: 54.444477 | P167: -124.26107 | Q167: Energy | R167: Clean Electricity | S167: Yes | T167: EN-CLEL
A168: 482 | B168: Western Bioenergy Inc. | C168: Merritt Green Energy Project | D168: BC | E168: Private | F168: 2017 | G168: 2018 | H168: ='mpi_dataset_summary_2017-2024'!$G168-'mpi_dataset_summary_2017-2024'!$F168+1 -> 2 | I168: Under Construction | J168: Under Construction | K168: =IF('mpi_dataset_summary_2017-2024'!$G168=2024,1,0) -> 0 | L168: =IF(J168="Under Construction",1,0) -> 1 | M168: 235 | N168: =_xlfn.PERCENTRANK.INC($M$2:$M$4056,M168) -> 0.527 | O168: 50.100761 | P168: -120.79375 | Q168: Energy | R168: Clean Electricity | S168: Yes | T168: EN-CLEL
A169: 484 | B169: Conuma Coal Resources Ltd. | C169: Belcourt/Saxon Coal Mines | D169: BC | E169: Private | F169: 2020 | G169: 2021 | H169: ='mpi_dataset_summary_2017-2024'!$G169-'mpi_dataset_summary_2017-2024'!$F169+1 -> 2 | I169: In Review | J169: In Review | K169: =IF('mpi_dataset_summary_2017-2024'!$G169=2024,1,0) -> 0 | L169: =IF(J169="Under Construction",1,0) -> 0 | M169: 100 | N169: =_xlfn.PERCENTRANK.INC($M$2:$M$4056,M169) -> 0.343 | O169: 54.711929 | P169: -120.95947 | Q169: Mining | R169: Coal | S169: No | T169: MIN-COAL
A170: 485 | B170: Conuma Coal Resources Ltd. | C170: Wolverine Coal Mine (Hermann Deposit) | D170: BC | E170: Private | F170: 2020 | G170: 2024 | H170: ='mpi_dataset_summary_2017-2024'!$G170-'mpi_dataset_summary_2017-2024'!$F170+1 -> 5 | I170: In Review | J170: Approved | K170: =IF('mpi_dataset_summary_2017-2024'!$G170=2024,1,0) -> 1 | L170: =IF(J170="Under Construction",1,0) -> 0 | M170: 55 | N170: =_xlfn.PERCENTRANK.INC($M$2:$M$4056,M170) -> 0.242 | O170: 55.266598 | P170: -120.87158 | Q170: Mining | R170: Coal | S170: No | T170: MIN-COAL
A171: 488 | B171: Western Copper and Gold Corporation | C171: Casino Mine | D171: YK | E171: Private | F171: 2017 | G171: 2024 | H171: ='mpi_dataset_summary_2017-2024'!$G171-'mpi_dataset_summary_2017-2024'!$F171+1 -> 8 | I171: In Review | J171: Announced & Planning | K171: =IF('mpi_dataset_summary_2017-2024'!$G171=2024,1,0) -> 1 | L171: =IF(J171="Under Construction",1,0) -> 0 | M171: 3617 | N171: =_xlfn.PERCENTRANK.INC($M$2:$M$4056,M171) -> 0.933 | O171: 62.739 | P171: -138.823 | Q171: Mining | R171: Precious Metal | S171: No | T171: MIN-PM
A172: 489 | B172: Western GeoPower Corporation - Ram Power Corp. | C172: South Meager Creek Geothermal Project | D172: BC | E172: Private | F172: 2017 | G172: 2017 | H172: ='mpi_dataset_summary_2017-2024'!$G172-'mpi_dataset_summary_2017-2024'!$F172+1 -> 1 | I172: Announced & Planning | J172: Announced & Planning | K172: =IF('mpi_dataset_summary_2017-2024'!$G172=2024,1,0) -> 0 | L172: =IF(J172="Under Construction",1,0) -> 0 | M172: 400 | N172: =_xlfn.PERCENTRANK.INC($M$2:$M$4056,M172) -> 0.635 | O172: 50.527332 | P172: -123.10811 | Q172: Energy | R172: Clean Electricity | S172: Yes | T172: EN-CLEL
A173: 490 | B173: Western Potash | C173: Milestone | D173: SK | E173: Private | F173: 2017 | G173: 2023 | H173: ='mpi_dataset_summary_2017-2024'!$G173-'mpi_dataset_summary_2017-2024'!$F173+1 -> 7 | I173: Approved | J173: Under Construction | K173: =IF('mpi_dataset_summary_2017-2024'!$G173=2024,1,0) -> 0 | L173: =IF(J173="Under Construction",1,0) -> 1 | M173: 149 | N173: =_xlfn.PERCENTRANK.INC($M$2:$M$4056,M173) -> 0.44 | O173: 50.118 | P173: -104.471 | Q173: Mining | R173: Critical Mineral | S173: Yes | T173: MIN-CM
A174: 492 | B174: Wildmare Wind Energy EP | C174: Wildmare Wind Energy Project | D174: BC | E174: Private | F174: 2017 | G174: 2017 | H174: ='mpi_dataset_summary_2017-2024'!$G174-'mpi_dataset_summary_2017-2024'!$F174+1 -> 1 | I174: In Review | J174: In Review | K174: =IF('mpi_dataset_summary_2017-2024'!$G174=2024,1,0) -> 0 | L174: =IF(J174="Under Construction",1,0) -> 0 | M174: 200 | N174: =_xlfn.PERCENTRANK.INC($M$2:$M$4056,M174) -> 0.491 | O174: 55.692287 | P174: -121.79041 | Q174: Energy | R174: Clean Electricity | S174: Yes | T174: EN-CLEL
A175: 499 | B175: Taseko Mines Ltd. | C175: Yellowhead (formerly Harper Creek) | D175: BC | E175: Private | F175: 2020 | G175: 2022 | H175: ='mpi_dataset_summary_2017-2024'!$G175-'mpi_dataset_summary_2017-2024'!$F175+1 -> 3 | I175: In Review | J175: Announced & Planning | K175: =IF('mpi_dataset_summary_2017-2024'!$G175=2024,1,0) -> 0 | L175: =IF(J175="Under Construction",1,0) -> 0 | M175: 1347 | N175: =_xlfn.PERCENTRANK.INC($M$2:$M$4056,M175) -> 0.853 | O175: 51.519 | P175: -119.817 | Q175: Mining | R175: Other | S175: No | T175: MIN-OTH
A176: 503 | B176: Alcoa | C176: Modernisation d'aluminerie | D176: QC | E176: Private | F176: 2017 | G176: 2019 | H176: ='mpi_dataset_summary_2017-2024'!$G176-'mpi_dataset_summary_2017-2024'!$F176+1 -> 3 | I176: Under Construction | J176: Under Construction | K176: =IF('mpi_dataset_summary_2017-2024'!$G176=2024,1,0) -> 0 | L176: =IF(J176="Under Construction",1,0) -> 1 | M176: 73 | N176: =_xlfn.PERCENTRANK.INC($M$2:$M$4056,M176) -> 0.286 | O176: 46.693725 | P176: -71.945135 | Q176: Mining | R176: Other | S176: No | T176: MIN-OTH
... A244: 659 | B244: TransCanada | C244: Heartland Pipeline Project | D244: AB | E244: Private | F244: 2017 | G244: 2021 | H244: ='mpi_dataset_summary_2017-2024'!$G244-'mpi_dataset_summary_2017-2024'!$F244+1 -> 5 | I244: Under Construction | J244: Approved | K244: =IF('mpi_dataset_summary_2017-2024'!$G244=2024,1,0) -> 0 | L244: =IF(J244="Under Construction",1,0) -> 0 | M244: 900 | N244: =_xlfn.PERCENTRANK.INC($M$2:$M$4056,M244) -> 0.794 | O244: 53.785042 | P244: -113.06602 | Q244: Energy | R244: Trans & Distr | S244: No | T244: EN-T&D
A245: 660 | B245: ATCO Pipelines | C245: Urban Pipeline Replacement Project | D245: AB | E245: Private | F245: 2017 | G245: 2021 | H245: ='mpi_dataset_summary_2017-2024'!$G245-'mpi_dataset_summary_2017-2024'!$F245+1 -> 5 | I245: Approved | J245: Under Construction | K245: =IF('mpi_dataset_summary_2017-2024'!$G245=2024,1,0) -> 0 | L245: =IF(J245="Under Construction",1,0) -> 1 | M245: 700 | N245: =_xlfn.PERCENTRANK.INC($M$2:$M$4056,M245) -> 0.743 | Q245: Energy | R245: Trans & Distr | S245: No | T245: EN-T&D
A246: 662 | B246: Prosper Petroleum | C246: Rigel Oil Sands Project | D246: AB | E246: Private | F246: 2017 | G246: 2022 | H246: ='mpi_dataset_summary_2017-2024'!$G246-'mpi_dataset_summary_2017-2024'!$F246+1 -> 6 | I246: In Review | J246: In Review | K246: =IF('mpi_dataset_summary_2017-2024'!$G246=2024,1,0) -> 0 | L246: =IF(J246="Under Construction",1,0) -> 0 | M246: 390 | N246: =_xlfn.PERCENTRANK.INC($M$2:$M$4056,M246) -> 0.632 | O246: 57.360001 | P246: -112.71 | Q246: Energy | R246: Oil & Gas - Upstream | S246: No | T246: EN-OG-U
A247: 668 | B247: Pteragen Canada | C247: Peace Butte Wind Farm | D247: AB | E247: Private | F247: 2017 | G247: 2020 | H247: ='mpi_dataset_summary_2017-2024'!$G247-'mpi_dataset_summary_2017-2024'!$F247+1 -> 4 | I247: Approved | J247: Approved | K247: =IF('mpi_dataset_summary_2017-2024'!$G247=2024,1,0) -> 0 | L247: =IF(J247="Under Construction",1,0) -> 0 | M247: 200 | N247: =_xlfn.PERCENTRANK.INC($M$2:$M$4056,M247) -> 0.491 | O247: 49.896077 | P247: -110.86766 | Q247: Energy | R247: Clean Electricity | S247: Yes | T247: EN-CLEL
A248: 669 | B248: FarmTech | C248: Ethanol plant | D248: ON | E248: Private | F248: 2017 | G248: 2017 | H248: ='mpi_dataset_summary_2017-2024'!$G248-'mpi_dataset_summary_2017-2024'!$F248+1 -> 1 | I248: Announced & Planning | J248: Announced & Planning | K248: =IF('mpi_dataset_summary_2017-2024'!$G248=2024,1,0) -> 0 | L248: =IF(J248="Under Construction",1,0) -> 0 | M248: 200 | N248: =_xlfn.PERCENTRANK.INC($M$2:$M$4056,M248) -> 0.491 | O248: 43.868006 | P248: -78.823288 | Q248: Energy | R248: Low Carbon Fuels | S248: Yes | T248: EN-LCF
A249: 671 | B249: Pembina Pipeline Corp. | C249: Saturn II Twinning | D249: AB | E249: Private | F249: 2017 | G249: 2017 | H249: ='mpi_dataset_summary_2017-2024'!$G249-'mpi_dataset_summary_2017-2024'!$F249+1 -> 1 | I249: Under Construction | J249: Under Construction | K249: =IF('mpi_dataset_summary_2017-2024'!$G249=2024,1,0) -> 0 | L249: =IF(J249="Under Construction",1,0) -> 1 | M249: 170 | N249: =_xlfn.PERCENTRANK.INC($M$2:$M$4056,M249) -> 0.465 | O249: 53.556136 | P249: -116.77268 | Q249: Energy | R249: Oil & Gas - Upstream | S249: No | T249: EN-OG-U
A250: 679 | B250: Gibson Energy Inc. | C250: Edmonton Terminal Expansion | D250: AB | E250: Private | F250: 2017 | G250: 2018 | H250: ='mpi_dataset_summary_2017-2024'!$G250-'mpi_dataset_summary_2017-2024'!$F250+1 -> 2 | I250: Announced & Planning | J250: Announced & Planning | K250: =IF('mpi_dataset_summary_2017-2024'!$G250=2024,1,0) -> 0 | L250: =IF(J250="Under Construction",1,0) -> 0 | M250: 100 | N250: =_xlfn.PERCENTRANK.INC($M$2:$M$4056,M250) -> 0.343 | O250: 53.5507 | P250: -113.3672 | Q250: Energy | R250: Oil & Gas - Downstream | S250: No | T250: EN-OG-D
A251: 684 | B251: Osum Oil Sands Corp. | C251: Sepiko Kesik Project | D251: AB | E251: Private | F251: 2017 | G251: 2024 | H251: ='mpi_dataset_summary_2017-2024'!$G251-'mpi_dataset_summary_2017-2024'!$F251+1 -> 8 | I251: In Review | J251: Approved | K251: =IF('mpi_dataset_summary_2017-2024'!$G251=2024,1,0) -> 1 | L251: =IF(J251="Under Construction",1,0) -> 0 | M251: 3200 | N251: =_xlfn.PERCENTRANK.INC($M$2:$M$4056,M251) -> 0.922 | O251: 56.688999 | P251: -113.131 | Q251: Energy | R251: Oil & Gas - Upstream | S251: No | T251: EN-OG-U
A252: 685 | B252: Resolute Forest Products | C252: Plant Modernization | D252: ON | E252: Private | F252: 2017 | G252: 2020 | H252: ='mpi_dataset_summary_2017-2024'!$G252-'mpi_dataset_summary_2017-2024'!$F252+1 -> 4 | I252: In Review | J252: In Review | K252: =IF('mpi_dataset_summary_2017-2024'!$G252=2024,1,0) -> 0 | L252: =IF(J252="Under Construction",1,0) -> 0 | M252: 0 | N252: =_xlfn.PERCENTRANK.INC($M$2:$M$4056,M252) -> 0 | O252: 48.359133 | P252: -89.233414 | Q252: Forest | R252: Other | S252: Yes | T252: FOR-OTH
A253: 688 | B253: Graymont Western Canada Inc. | C253: Giscome Quarry and Lime Plant Project | D253: BC | E253: Private | F253: 2017 | G253: 2024 | H253: ='mpi_dataset_summary_2017-2024'!$G253-'mpi_dataset_summary_2017-2024'!$F253+1 -> 8 | I253: In Review | J253: Approved | K253: =IF('mpi_dataset_summary_2017-2024'!$G253=2024,1,0) -> 1 | L253: =IF(J253="Under Construction",1,0) -> 0 | M253: 130 | N253: =_xlfn.PERCENTRANK.INC($M$2:$M$4056,M253) -> 0.412 | O253: 54.052936 | P253: -122.28528 | Q253: Mining | R253: Other | S253: No | T253: MIN-OTH
A254: 689 | B254: Innergex Wind Energy Inc and Saik'uz First Nation | C254: Nulki Hills, 30 km south of Vanderhoof | D254: BC | E254: Private | F254: 2017 | G254: 2023 | H254: ='mpi_dataset_summary_2017-2024'!$G254-'mpi_dataset_summary_2017-2024'!$F254+1 -> 7 | I254: In Review | J254: In Review | K254: =IF('mpi_dataset_summary_2017-2024'!$G254=2024,1,0) -> 0 | L254: =IF(J254="Under Construction",1,0) -> 0 | M254: 56 | N254: =_xlfn.PERCENTRANK.INC($M$2:$M$4056,M254) -> 0.247 | O254: 53.926988 | P254: -124.0891 | Q254: Energy | R254: Clean Electricity | S254: Yes | T254: EN-CLEL
A255: 690 | B255: Innergex Renewable Energy Inc. | C255: Statlu Creek Hydroelectric Project | D255: BC | E255: Private | F255: 2019 | G255: 2019 | H255: ='mpi_dataset_summary_2017-2024'!$G255-'mpi_dataset_summary_2017-2024'!$F255+1 -> 1 | I255: Announced & Planning | J255: Announced & Planning | K255: =IF('mpi_dataset_summary_2017-2024'!$G255=2024,1,0) -> 0 | L255: =IF(J255="Under Construction",1,0) -> 0 | M255: 25 | N255: =_xlfn.PERCENTRANK.INC($M$2:$M$4056,M255) -> 0.125 | O255: 49.2817 | P255: -121.9308 | Q255: Energy | R255: Clean Electricity | S255: Yes | T255: EN-CLEL
A256: 691 | B256: EDF Energies Nouvelles | C256: Sundance Wind Project | D256: BC | E256: Private | F256: 2018 | G256: 2018 | H256: ='mpi_dataset_summary_2017-2024'!$G256-'mpi_dataset_summary_2017-2024'!$F256+1 -> 1 | I256: In Review | J256: In Review | K256: =IF('mpi_dataset_summary_2017-2024'!$G256=2024,1,0) -> 0 | L256: =IF(J256="Under Construction",1,0) -> 0 | M256: 600 | N256: =_xlfn.PERCENTRANK.INC($M$2:$M$4056,M256) -> 0.714 | O256: 55.334152 | P256: -121.10027 | Q256: Energy | R256: Clean Electricity | S256: Yes | T256: EN-CLEL
A257: 692 | B257: EDF Renouvelables | C257: Taylor Wind Project | D257: BC | E257: Private | F257: 2017 | G257: 2024 | H257: ='mpi_dataset_summary_2017-2024'!$G257-'mpi_dataset_summary_2017-2024'!$F257+1 -> 8 | I257: In Review | J257: In Review | K257: =IF('mpi_dataset_summary_2017-2024'!$G257=2024,1,0) -> 1 | L257: =IF(J257="Under Construction",1,0) -> 0 | M257: 900 | N257: =_xlfn.PERCENTRANK.INC($M$2:$M$4056,M257) -> 0.794 | O257: 55.999947 | P257: -120.76405 | Q257: Energy | R257: Clean Electricity | S257: Yes | T257: EN-CLEL
... A277: 752 | B277: Swift Power Corp. | C277: Jervis Inlet Hydro Project | D277: BC | E277: Private | F277: 2017 | G277: 2017 | H277: ='mpi_dataset_summary_2017-2024'!$G277-'mpi_dataset_summary_2017-2024'!$F277+1 -> 1 | I277: Announced & Planning | J277: Announced & Planning | K277: =IF('mpi_dataset_summary_2017-2024'!$G277=2024,1,0) -> 0 | L277: =IF(J277="Under Construction",1,0) -> 0 | M277: 25 | N277: =_xlfn.PERCENTRANK.INC($M$2:$M$4056,M277) -> 0.125 | O277: 49.8638 | P277: -123.863 | Q277: Energy | R277: Clean Electricity | S277: Yes | T277: EN-CLEL
A278: 753 | B278: Kruger Energy Inc. | C278: Maselpanik Creek Hydro Project | D278: BC | E278: Private | F278: 2017 | G278: 2024 | H278: ='mpi_dataset_summary_2017-2024'!$G278-'mpi_dataset_summary_2017-2024'!$F278+1 -> 8 | I278: Announced & Planning | J278: In Review | K278: =IF('mpi_dataset_summary_2017-2024'!$G278=2024,1,0) -> 1 | L278: =IF(J278="Under Construction",1,0) -> 0 | M278: 400 | N278: =_xlfn.PERCENTRANK.INC($M$2:$M$4056,M278) -> 0.635 | O278: 49.089 | Q278: Energy | R278: Clean Electricity | S278: Yes | T278: EN-CLEL
A279: 754 | B279: Pacific Coastal Wave Energy Corp. | C279: Wave Energy Project | D279: BC | E279: Private | F279: 2017 | G279: 2024 | H279: ='mpi_dataset_summary_2017-2024'!$G279-'mpi_dataset_summary_2017-2024'!$F279+1 -> 8 | I279: Announced & Planning | J279: Announced & Planning | K279: =IF('mpi_dataset_summary_2017-2024'!$G279=2024,1,0) -> 1 | L279: =IF(J279="Under Construction",1,0) -> 0 | M279: 20 | N279: =_xlfn.PERCENTRANK.INC($M$2:$M$4056,M279) -> 0.089 | O279: 48.9206 | P279: -125.5448 | Q279: Energy | R279: Clean Electricity | S279: Yes | T279: EN-CLEL
A280: 757 | B280: Innergex Renewable Energy Inc. | C280: Shovel Creek Hydroelectric Project | D280: BC | E280: Private | F280: 2020 | G280: 2024 | H280: ='mpi_dataset_summary_2017-2024'!$G280-'mpi_dataset_summary_2017-2024'!$F280+1 -> 5 | I280: In Review | J280: In Review | K280: =IF('mpi_dataset_summary_2017-2024'!$G280=2024,1,0) -> 1 | L280: =IF(J280="Under Construction",1,0) -> 0 | M280: 40 | N280: =_xlfn.PERCENTRANK.INC($M$2:$M$4056,M280) -> 0.178 | O280: 49.7212 | P280: -121.8148 | Q280: Energy | R280: Clean Electricity | S280: Yes | T280: EN-CLEL
A281: 758 | B281: Pristine Power Inc./Cheslatta Forest Products | C281: Cheslatta Green Energy Project | D281: BC | E281: Private | F281: 2017 | G281: 2024 | H281: ='mpi_dataset_summary_2017-2024'!$G281-'mpi_dataset_summary_2017-2024'!$F281+1 -> 8 | I281: Announced & Planning | J281: In Review | K281: =IF('mpi_dataset_summary_2017-2024'!$G281=2024,1,0) -> 1 | L281: =IF(J281="Under Construction",1,0) -> 0 | M281: 46 | N281: =_xlfn.PERCENTRANK.INC($M$2:$M$4056,M281) -> 0.204 | O281: 53.5792 | P281: -124.95 | Q281: Energy | R281: Clean Electricity | S281: Yes | T281: EN-CLEL
A282: 759 | B282: KMC Power | C282: Tamihi Creek Hydro Project | D282: BC | E282: Private | F282: 2017 | G282: 2024 | H282: ='mpi_dataset_summary_2017-2024'!$G282-'mpi_dataset_summary_2017-2024'!$F282+1 -> 8 | I282: In Review | J282: In Review | K282: =IF('mpi_dataset_summary_2017-2024'!$G282=2024,1,0) -> 1 | L282: =IF(J282="Under Construction",1,0) -> 0 | M282: 50 | N282: =_xlfn.PERCENTRANK.INC($M$2:$M$4056,M282) -> 0.214 | O282: 49.0461 | P282: -121.8196 | Q282: Energy | R282: Clean Electricity | S282: Yes | T282: EN-CLEL
A283: 761 | B283: TransAlta Corporation - Sorgente | C283: Clemina Creek Hydro Project | D283: BC | E283: Private | F283: 2021 | G283: 2022 | H283: ='mpi_dataset_summary_2017-2024'!$G283-'mpi_dataset_summary_2017-2024'!$F283+1 -> 2 | I283: Under Construction | J283: Under Construction | K283: =IF('mpi_dataset_summary_2017-2024'!$G283=2024,1,0) -> 0 | L283: =IF(J283="Under Construction",1,0) -> 1 | M283: 45 | N283: =_xlfn.PERCENTRANK.INC($M$2:$M$4056,M283) -> 0.194 | O283: 52.763464 | P283: -119.26826 | Q283: Energy | R283: Clean Electricity | S283: Yes | T283: EN-CLEL
A284: 762 | B284: Kitsault Hydroelectric Corp. | C284: Kitsault River and Homestake Creek Hydro Project | D284: BC | E284: Private | F284: 2017 | G284: 2017 | H284: ='mpi_dataset_summary_2017-2024'!$G284-'mpi_dataset_summary_2017-2024'!$F284+1 -> 1 | I284: Under Construction | J284: Under Construction | K284: =IF('mpi_dataset_summary_2017-2024'!$G284=2024,1,0) -> 0 | L284: =IF(J284="Under Construction",1,0) -> 1 | M284: 21 | N284: =_xlfn.PERCENTRANK.INC($M$2:$M$4056,M284) -> 0.104 | O284: 55.483636 | P284: -124.4901 | Q284: Energy | R284: Clean Electricity | S284: Yes | T284: EN-CLEL
A285: 763 | B285: Highwater Power Corporation | C285: Kookipi Creek Water Power Project | D285: BC | E285: Private | F285: 2017 | G285: 2020 | H285: ='mpi_dataset_summary_2017-2024'!$G285-'mpi_dataset_summary_2017-2024'!$F285+1 -> 4 | I285: Announced & Planning | J285: Announced & Planning | K285: =IF('mpi_dataset_summary_2017-2024'!$G285=2024,1,0) -> 0 | L285: =IF(J285="Under Construction",1,0) -> 0 | M285: 20 | N285: =_xlfn.PERCENTRANK.INC($M$2:$M$4056,M285) -> 0.089 | O285: 49.963971 | P285: -121.6835 | Q285: Energy | R285: Clean Electricity | S285: Yes | T285: EN-LCF
A286: 764 | B286: Highwater Power Corporation Altagas Ltd. | C286: Log Creek Water Power Project | D286: BC | E286: Private | F286: 2017 | G286: 2024 | H286: ='mpi_dataset_summary_2017-2024'!$G286-'mpi_dataset_summary_2017-2024'!$F286+1 -> 8 | I286: Announced & Planning | J286: Announced & Planning | K286: =IF('mpi_dataset_summary_2017-2024'!$G286=2024,1,0) -> 1 | L286: =IF(J286="Under Construction",1,0) -> 0 | M286: 20 | N286: =_xlfn.PERCENTRANK.INC($M$2:$M$4056,M286) -> 0.089 | O286: 50.05884 | P286: -121.7174 | Q286: Energy | R286: Clean Electricity | S286: Yes | T286: EN-LCF
A287: 768 | B287: Hiranandani Group / AC LNG | C287: AC LNG | D287: NS | E287: Private | F287: 2017 | G287: 2019 | H287: ='mpi_dataset_summary_2017-2024'!$G287-'mpi_dataset_summary_2017-2024'!$F287+1 -> 3 | I287: In Review | J287: In Review | K287: =IF('mpi_dataset_summary_2017-2024'!$G287=2024,1,0) -> 0 | L287: =IF(J287="Under Construction",1,0) -> 0 | M287: 3000 | N287: =_xlfn.PERCENTRANK.INC($M$2:$M$4056,M287) -> 0.921 | O287: 45.529312 | P287: -61.293472 | Q287: Energy | R287: Oil & Gas - Downstream | S287: No | T287: EN-OG-D
A288: 770 | B288: TransAlta | C288: Sundance 7 Gas fired power plant | D288: AB | E288: Private | F288: 2019 | G288: 2020 | H288: ='mpi_dataset_summary_2017-2024'!$G288-'mpi_dataset_summary_2017-2024'!$F288+1 -> 2 | I288: Approved | J288: Approved | K288: =IF('mpi_dataset_summary_2017-2024'!$G288=2024,1,0) -> 0 | L288: =IF(J288="Under Construction",1,0) -> 0 | M288: 1600 | N288: =_xlfn.PERCENTRANK.INC($M$2:$M$4056,M288) -> 0.873 | O288: 53.3027 | P288: -114.3326 | Q288: Energy | R288: NG Power Gen | S288: Yes | T288: EN-LCF
A289: 774 | B289: Ironhead First Nations Partnership | C289: Great Spirit Power Project | D289: AB | E289: Private | F289: 2017 | G289: 2020 | H289: ='mpi_dataset_summary_2017-2024'!$G289-'mpi_dataset_summary_2017-2024'!$F289+1 -> 4 | I289: Announced & Planning | J289: Announced & Planning | K289: =IF('mpi_dataset_summary_2017-2024'!$G289=2024,1,0) -> 0 | L289: =IF(J289="Under Construction",1,0) -> 0 | M289: 1500 | N289: =_xlfn.PERCENTRANK.INC($M$2:$M$4056,M289) -> 0.864 | O289: 53.5485 | P289: -114.269 | Q289: Energy | R289: Low Carbon Fuels | S289: Yes | T289: EN-LCF
A290: 775 | B290: ATCO Power | C290: ATCO Heartland Generating Station | D290: AB | E290: Private | F290: 2017 | G290: 2019 | H290: ='mpi_dataset_summary_2017-2024'!$G290-'mpi_dataset_summary_2017-2024'!$F290+1 -> 3 | I290: Approved | J290: Approved | K290: =IF('mpi_dataset_summary_2017-2024'!$G290=2024,1,0) -> 0 | L290: =IF(J290="Under Construction",1,0) -> 0 | M290: 800 | N290: =_xlfn.PERCENTRANK.INC($M$2:$M$4056,M290) -> 0.777 | O290: 53.762901 | P290: -113.0651 | Q290: Energy | R290: Other | S290: Yes | T290: EN-OTH
... A374: 938 | B374: Cedar LNG (partnership between Pembina Pipeline Corporation and Haisla Nation) | C374: Cedar LNG | D374: BC | E374: Private | F374: 2017 | G374: 2024 | H374: ='mpi_dataset_summary_2017-2024'!$G374-'mpi_dataset_summary_2017-2024'!$F374+1 -> 8 | I374: In Review | J374: Announced & Planning | K374: =IF('mpi_dataset_summary_2017-2024'!$G374=2024,1,0) -> 1 | L374: =IF(J374="Under Construction",1,0) -> 0 | M374: 4600 | N374: =_xlfn.PERCENTRANK.INC($M$2:$M$4056,M374) -> 0.946 | O374: 53.925411 | P374: -128.72791 | Q374: Energy | R374: Oil & Gas - Downstream | S374: No | T374: EN-OG-D
A375: 939 | B375: NewTimes Energy Ltd. | C375: NewTimes Energy | D375: BC | E375: Private | F375: 2017 | G375: 2021 | H375: ='mpi_dataset_summary_2017-2024'!$G375-'mpi_dataset_summary_2017-2024'!$F375+1 -> 5 | I375: In Review | J375: Announced & Planning | K375: =IF('mpi_dataset_summary_2017-2024'!$G375=2024,1,0) -> 0 | L375: =IF(J375="Under Construction",1,0) -> 0 | M375: 0 | N375: =_xlfn.PERCENTRANK.INC($M$2:$M$4056,M375) -> 0 | Q375: Energy | R375: Clean Electricity | S375: Yes | T375: EN-CLEL
A376: 942 | B376: Watson Island LNG Corporation | C376: Watson Island LNG | D376: BC | E376: Private | F376: 2017 | G376: 2024 | H376: ='mpi_dataset_summary_2017-2024'!$G376-'mpi_dataset_summary_2017-2024'!$F376+1 -> 8 | I376: Announced & Planning | J376: Announced & Planning | K376: =IF('mpi_dataset_summary_2017-2024'!$G376=2024,1,0) -> 1 | L376: =IF(J376="Under Construction",1,0) -> 0 | M376: 270 | N376: =_xlfn.PERCENTRANK.INC($M$2:$M$4056,M376) -> 0.558 | Q376: Energy | R376: Oil & Gas - Downstream | S376: No | T376: EN-OG-D
A377: 943 | B377: Tilbury Jetty Marine Partnership (Fortis, Seaspan, Shell) | C377: Tilbury Marine Jetty | D377: BC | E377: Private | F377: 2017 | G377: 2024 | H377: ='mpi_dataset_summary_2017-2024'!$G377-'mpi_dataset_summary_2017-2024'!$F377+1 -> 8 | I377: In Review | J377: In Review | K377: =IF('mpi_dataset_summary_2017-2024'!$G377=2024,1,0) -> 1 | L377: =IF(J377="Under Construction",1,0) -> 0 | M377: 1100 | N377: =_xlfn.PERCENTRANK.INC($M$2:$M$4056,M377) -> 0.822 | O377: 49.141798 | P377: -123.02351 | Q377: Energy | R377: Oil & Gas - Downstream | S377: No | T377: EN-OG-D
A378: 944 | B378: Vale Newfoundland and Labrador Limited | C378: Underground Mine Development | D378: NL | E378: Private | F378: 2017 | G378: 2020 | H378: ='mpi_dataset_summary_2017-2024'!$G378-'mpi_dataset_summary_2017-2024'!$F378+1 -> 4 | I378: Under Construction | J378: Under Construction | K378: =IF('mpi_dataset_summary_2017-2024'!$G378=2024,1,0) -> 0 | L378: =IF(J378="Under Construction",1,0) -> 1 | M378: 2551.36 | N378: =_xlfn.PERCENTRANK.INC($M$2:$M$4056,M378) -> 0.916 | O378: 56.339569 | P378: -62.096443 | Q378: Mining | R378: Precious Metal | S378: No | T378: MIN-PM
A379: 946 | B379: Unibord | C379: Mill upgrade | D379: QC | E379: Private | F379: 2017 | G379: 2018 | H379: ='mpi_dataset_summary_2017-2024'!$G379-'mpi_dataset_summary_2017-2024'!$F379+1 -> 2 | I379: Announced & Planning | J379: Announced & Planning | K379: =IF('mpi_dataset_summary_2017-2024'!$G379=2024,1,0) -> 0 | L379: =IF(J379="Under Construction",1,0) -> 0 | M379: 53 | N379: =_xlfn.PERCENTRANK.INC($M$2:$M$4056,M379) -> 0.236 | O379: 48.11554 | P379: -77.778944 | Q379: Forest | R379: Pulp & Paper | S379: No | T379: FOR-P&P
A380: 947 | B380: TransCanada | C380: Eastern Mainline | D380: ON | E380: Private | F380: 2017 | G380: 2017 | H380: ='mpi_dataset_summary_2017-2024'!$G380-'mpi_dataset_summary_2017-2024'!$F380+1 -> 1 | I380: In Review | J380: In Review | K380: =IF('mpi_dataset_summary_2017-2024'!$G380=2024,1,0) -> 0 | L380: =IF(J380="Under Construction",1,0) -> 0 | M380: 1500 | N380: =_xlfn.PERCENTRANK.INC($M$2:$M$4056,M380) -> 0.864 | O380: 43.728668 | P380: -79.2751 | Q380: Energy | R380: Trans & Distr | S380: No | T380: EN-T&D
A381: 949 | B381: Hydro-Quebec | C381: Ligne √† 735 kV de la Chamouchouane-BD√é | D381: QC | E381: Public | F381: 2017 | G381: 2017 | H381: ='mpi_dataset_summary_2017-2024'!$G381-'mpi_dataset_summary_2017-2024'!$F381+1 -> 1 | I381: Under Construction | J381: Under Construction | K381: =IF('mpi_dataset_summary_2017-2024'!$G381=2024,1,0) -> 0 | L381: =IF(J381="Under Construction",1,0) -> 1 | M381: 1340 | N381: =_xlfn.PERCENTRANK.INC($M$2:$M$4056,M381) -> 0.85 | O381: 45.7217 | P381: -73.7072 | Q381: Energy | R381: Clean Electricity | S381: Yes | T381: EN-CLEL
A382: 951 | B382: Dominion Diamonds Corp. | C382: Ekati Diamond Mine Expansion - Jay Pipe | D382: NT | E382: Private | F382: 2017 | G382: 2019 | H382: ='mpi_dataset_summary_2017-2024'!$G382-'mpi_dataset_summary_2017-2024'!$F382+1 -> 3 | I382: Approved | J382: Approved | K382: =IF('mpi_dataset_summary_2017-2024'!$G382=2024,1,0) -> 0 | L382: =IF(J382="Under Construction",1,0) -> 0 | M382: 840 | N382: =_xlfn.PERCENTRANK.INC($M$2:$M$4056,M382) -> 0.786 | O382: 64.445237 | P382: -110.69559 | Q382: Mining | R382: Precious Metal | S382: No | T382: MIN-PM
A383: 952 | B383: Glencore | C383: Raglan(phase 2) | D383: QC | E383: Private | F383: 2017 | G383: 2022 | H383: ='mpi_dataset_summary_2017-2024'!$G383-'mpi_dataset_summary_2017-2024'!$F383+1 -> 6 | I383: In Review | J383: Under Construction | K383: =IF('mpi_dataset_summary_2017-2024'!$G383=2024,1,0) -> 0 | L383: =IF(J383="Under Construction",1,0) -> 1 | M383: 1000 | N383: =_xlfn.PERCENTRANK.INC($M$2:$M$4056,M383) -> 0.805 | O383: 61.6877 | P383: -73.6772 | Q383: Mining | R383: Other | S383: No | T383: MIN-OTH
A384: 954 | B384: AltaGas Ltd. | C384: Fort St. John Liquids Hub | D384: BC | E384: Private | F384: 2017 | G384: 2019 | H384: ='mpi_dataset_summary_2017-2024'!$G384-'mpi_dataset_summary_2017-2024'!$F384+1 -> 3 | I384: Announced & Planning | J384: Under Construction | K384: =IF('mpi_dataset_summary_2017-2024'!$G384=2024,1,0) -> 0 | L384: =IF(J384="Under Construction",1,0) -> 1 | M384: 100 | N384: =_xlfn.PERCENTRANK.INC($M$2:$M$4056,M384) -> 0.343 | O384: 56.246614 | P384: -120.84765 | Q384: Energy | R384: Other | S384: Yes | T384: EN-OTH
A385: 955 | B385: AltaGas Ltd. | C385: Ridley Island Propane Export Terminal | D385: BC | E385: Private | F385: 2017 | G385: 2018 | H385: ='mpi_dataset_summary_2017-2024'!$G385-'mpi_dataset_summary_2017-2024'!$F385+1 -> 2 | I385: Approved | J385: Under Construction | K385: =IF('mpi_dataset_summary_2017-2024'!$G385=2024,1,0) -> 0 | L385: =IF(J385="Under Construction",1,0) -> 1 | M385: 450 | N385: =_xlfn.PERCENTRANK.INC($M$2:$M$4056,M385) -> 0.655 | O385: 54.224372 | P385: -130.32819 | Q385: Energy | R385: Oil & Gas - Downstream | S385: No | T385: EN-OG-D
A386: 956 | B386: Altalink | C386: Chapel Rock to Pincher Creek Area Transmission Development | D386: AB | E386: Private | F386: 2017 | G386: 2024 | H386: ='mpi_dataset_summary_2017-2024'!$G386-'mpi_dataset_summary_2017-2024'!$F386+1 -> 8 | I386: Announced & Planning | J386: Announced & Planning | K386: =IF('mpi_dataset_summary_2017-2024'!$G386=2024,1,0) -> 1 | L386: =IF(J386="Under Construction",1,0) -> 0 | M386: 500 | N386: =_xlfn.PERCENTRANK.INC($M$2:$M$4056,M386) -> 0.678 | O386: 49.739198 | P386: -114.30065 | Q386: Energy | R386: Trans & Distr | S386: No | T386: EN-T&D
A387: 957 | B387: Atrum Coal | C387: Groundhog Project Anthracite Coal Mine | D387: BC | E387: Private | F387: 2017 | G387: 2024 | H387: ='mpi_dataset_summary_2017-2024'!$G387-'mpi_dataset_summary_2017-2024'!$F387+1 -> 8 | I387: Announced & Planning | J387: Announced & Planning | K387: =IF('mpi_dataset_summary_2017-2024'!$G387=2024,1,0) -> 1 | L387: =IF(J387="Under Construction",1,0) -> 0 | M387: 600 | N387: =_xlfn.PERCENTRANK.INC($M$2:$M$4056,M387) -> 0.714 | O387: 56.70066 | P387: -128.76229 | Q387: Mining | R387: Coal | S387: No | T387: MIN-COAL
A388: 958 | B388: BC Hydro | C388: Tofino and Ahousaht LongTerm Power Supply | D388: BC | E388: Public | F388: 2017 | G388: 2020 | H388: ='mpi_dataset_summary_2017-2024'!$G388-'mpi_dataset_summary_2017-2024'!$F388+1 -> 4 | I388: In Review | J388: Under Construction | K388: =IF('mpi_dataset_summary_2017-2024'!$G388=2024,1,0) -> 0 | L388: =IF(J388="Under Construction",1,0) -> 1 | M388: 21 | N388: =_xlfn.PERCENTRANK.INC($M$2:$M$4056,M388) -> 0.104 | O388: 49.283514 | P388: -125.67942 | Q388: Energy | R388: Trans & Distr | S388: No | T388: EN-LCF
... A411: 984 | B411: Terasen Gas/Kelowna City | C411: Kelowna City Centre Renewable Energy System | D411: BC | E411: Private | F411: 2017 | G411: 2019 | H411: ='mpi_dataset_summary_2017-2024'!$G411-'mpi_dataset_summary_2017-2024'!$F411+1 -> 3 | I411: Announced & Planning | J411: Announced & Planning | K411: =IF('mpi_dataset_summary_2017-2024'!$G411=2024,1,0) -> 0 | L411: =IF(J411="Under Construction",1,0) -> 0 | M411: 38 | N411: =_xlfn.PERCENTRANK.INC($M$2:$M$4056,M411) -> 0.174 | O411: 49.888107 | P411: -119.48557 | Q411: Energy | R411: Clean Electricity | S411: Yes | T411: EN-CLEL
A412: 985 | B412: TransAlta - Sorgente | C412: TransAlta - Sorgente | D412: BC | E412: Private | F412: 2017 | G412: 2017 | H412: ='mpi_dataset_summary_2017-2024'!$G412-'mpi_dataset_summary_2017-2024'!$F412+1 -> 1 | I412: Announced & Planning | J412: Announced & Planning | K412: =IF('mpi_dataset_summary_2017-2024'!$G412=2024,1,0) -> 0 | L412: =IF(J412="Under Construction",1,0) -> 0 | M412: 45 | N412: =_xlfn.PERCENTRANK.INC($M$2:$M$4056,M412) -> 0.194 | P412: -119.33485 | Q412: Energy | R412: Waste Biomass | S412: Yes | T412: EN-BIO
A413: 987 | B413: Veresen Midstream | C413: Tower Gas Plant | D413: BC | E413: Private | F413: 2017 | G413: 2017 | H413: ='mpi_dataset_summary_2017-2024'!$G413-'mpi_dataset_summary_2017-2024'!$F413+1 -> 1 | I413: Approved | J413: Approved | K413: =IF('mpi_dataset_summary_2017-2024'!$G413=2024,1,0) -> 0 | L413: =IF(J413="Under Construction",1,0) -> 0 | M413: 715 | N413: =_xlfn.PERCENTRANK.INC($M$2:$M$4056,M413) -> 0.751 | O413: 56.002882 | P413: -120.68527 | Q413: Energy | R413: Oil & Gas - Downstream | S413: No | T413: EN-OG-D
A414: 988 | B414: Zero Emission Energy Developments Inc. | C414: Septimus Creek Wind Power Project | D414: BC | E414: Private | F414: 2017 | G414: 2019 | H414: ='mpi_dataset_summary_2017-2024'!$G414-'mpi_dataset_summary_2017-2024'!$F414+1 -> 3 | I414: Under Construction | J414: Under Construction | K414: =IF('mpi_dataset_summary_2017-2024'!$G414=2024,1,0) -> 0 | L414: =IF(J414="Under Construction",1,0) -> 1 | M414: 45 | N414: =_xlfn.PERCENTRANK.INC($M$2:$M$4056,M414) -> 0.194 | O414: 56.07097 | P414: -120.90042 | Q414: Energy | R414: Clean Electricity | S414: Yes | T414: EN-CLEL
A415: 989 | B415: Zero Emission Energy Developments Inc. | C415: Pennask Wind Power Project | D415: BC | E415: Private | F415: 2017 | G415: 2017 | H415: ='mpi_dataset_summary_2017-2024'!$G415-'mpi_dataset_summary_2017-2024'!$F415+1 -> 1 | I415: Under Construction | J415: Under Construction | K415: =IF('mpi_dataset_summary_2017-2024'!$G415=2024,1,0) -> 0 | L415: =IF(J415="Under Construction",1,0) -> 1 | M415: 45 | N415: =_xlfn.PERCENTRANK.INC($M$2:$M$4056,M415) -> 0.194 | O415: 49.921589 | P415: -120.10992 | Q415: Energy | R415: Clean Electricity | S415: Yes | T415: EN-CLEL
A416: 990 | B416: Zero Emission Energy Developments Inc. | C416: Shinish Creek Wind Power Project | D416: BC | E416: Private | F416: 2017 | G416: 2017 | H416: ='mpi_dataset_summary_2017-2024'!$G416-'mpi_dataset_summary_2017-2024'!$F416+1 -> 1 | I416: Under Construction | J416: Under Construction | K416: =IF('mpi_dataset_summary_2017-2024'!$G416=2024,1,0) -> 0 | L416: =IF(J416="Under Construction",1,0) -> 1 | M416: 45 | N416: =_xlfn.PERCENTRANK.INC($M$2:$M$4056,M416) -> 0.194 | O416: 49.685672 | P416: -120.10666 | Q416: Energy | R416: Clean Electricity | S416: Yes | T416: EN-CLEL
A417: 993 | B417: MRC de Lotbini√®re / RES Canada et municipalit√©s de Saint-S√©verin et de Saint-Sylvestre | C417: Parc √©olien Mont Sainte-Marguerite | D417: QC | E417: Private | F417: 2017 | G417: 2017 | H417: ='mpi_dataset_summary_2017-2024'!$G417-'mpi_dataset_summary_2017-2024'!$F417+1 -> 1 | I417: Under Construction | J417: Under Construction | K417: =IF('mpi_dataset_summary_2017-2024'!$G417=2024,1,0) -> 0 | L417: =IF(J417="Under Construction",1,0) -> 1 | M417: 300 | N417: =_xlfn.PERCENTRANK.INC($M$2:$M$4056,M417) -> 0.574 | O417: 46.3343 | P417: -71.1332 | Q417: Energy | R417: Other | S417: Yes | T417: EN-OTH
A418: 994 | B418: EDF EN Canada, Alliance √âolienne de l‚ÄôEst et R√©gie intermunicipale Gasp√©sie | C418: Parc √©olien Nicolas-Riou | D418: QC | E418: Private | F418: 2017 | G418: 2017 | H418: ='mpi_dataset_summary_2017-2024'!$G418-'mpi_dataset_summary_2017-2024'!$F418+1 -> 1 | I418: Under Construction | J418: Under Construction | K418: =IF('mpi_dataset_summary_2017-2024'!$G418=2024,1,0) -> 0 | L418: =IF(J418="Under Construction",1,0) -> 1 | M418: 500 | N418: =_xlfn.PERCENTRANK.INC($M$2:$M$4056,M418) -> 0.678 | Q418: Energy | R418: Other | S418: Yes | T418: EN-OTH
A419: 996 | B419: AltaLink, ATCO | C419: Central East Area Transmission Development | D419: AB | E419: Private | F419: 2019 | G419: 2024 | H419: ='mpi_dataset_summary_2017-2024'!$G419-'mpi_dataset_summary_2017-2024'!$F419+1 -> 6 | I419: Announced & Planning | J419: Under Construction | K419: =IF('mpi_dataset_summary_2017-2024'!$G419=2024,1,0) -> 1 | L419: =IF(J419="Under Construction",1,0) -> 1 | M419: 332 | N419: =_xlfn.PERCENTRANK.INC($M$2:$M$4056,M419) -> 0.597 | O419: 52.848469 | P419: -110.89951 | Q419: Energy | R419: Trans & Distr | S419: No | T419: EN-T&D
A420: 997 | B420: AltaLink | C420: Edmonton Region 240kV Line Upgrades | D420: AB | E420: Private | F420: 2017 | G420: 2017 | H420: ='mpi_dataset_summary_2017-2024'!$G420-'mpi_dataset_summary_2017-2024'!$F420+1 -> 1 | I420: Under Construction | J420: Under Construction | K420: =IF('mpi_dataset_summary_2017-2024'!$G420=2024,1,0) -> 0 | L420: =IF(J420="Under Construction",1,0) -> 1 | M420: 114.01 | N420: =_xlfn.PERCENTRANK.INC($M$2:$M$4056,M420) -> 0.38 | O420: 53.54194 | P420: -113.49162 | Q420: Energy | R420: Trans & Distr | S420: No | T420: EN-T&D
A421: 998 | B421: AltaLink | C421: Fidler Substation Connection | D421: AB | E421: Private | F421: 2017 | G421: 2017 | H421: ='mpi_dataset_summary_2017-2024'!$G421-'mpi_dataset_summary_2017-2024'!$F421+1 -> 1 | I421: In Review | J421: In Review | K421: =IF('mpi_dataset_summary_2017-2024'!$G421=2024,1,0) -> 0 | L421: =IF(J421="Under Construction",1,0) -> 0 | M421: 86.91 | N421: =_xlfn.PERCENTRANK.INC($M$2:$M$4056,M421) -> 0.324 | Q421: Energy | R421: Trans & Distr | S421: No | T421: EN-T&D
A422: 999 | B422: AltaLink | C422: Foothills Area Transmission Development - Third Circuit | D422: AB | E422: Private | F422: 2017 | G422: 2017 | H422: ='mpi_dataset_summary_2017-2024'!$G422-'mpi_dataset_summary_2017-2024'!$F422+1 -> 1 | I422: In Review | J422: In Review | K422: =IF('mpi_dataset_summary_2017-2024'!$G422=2024,1,0) -> 0 | L422: =IF(J422="Under Construction",1,0) -> 0 | M422: 25.53 | N422: =_xlfn.PERCENTRANK.INC($M$2:$M$4056,M422) -> 0.134 | Q422: Energy | R422: Trans & Distr | S422: No | T422: EN-T&D
A423: 1000 | B423: AltaLink | C423: Fort McMurray West 500 kV Transmission Project | D423: AB | E423: Private | F423: 2017 | G423: 2019 | H423: ='mpi_dataset_summary_2017-2024'!$G423-'mpi_dataset_summary_2017-2024'!$F423+1 -> 3 | I423: Under Construction | J423: Under Construction | K423: =IF('mpi_dataset_summary_2017-2024'!$G423=2024,1,0) -> 0 | L423: =IF(J423="Under Construction",1,0) -> 1 | M423: 1600 | N423: =_xlfn.PERCENTRANK.INC($M$2:$M$4056,M423) -> 0.873 | O423: 53.344208 | P423: -114.30368 | Q423: Energy | R423: Trans & Distr | S423: No | T423: EN-T&D
A424: 1002 | B424: Ministere du developpement durable, de l'environnement et des parcs | C424: Refection du barrage des Quinze | D424: QC | E424: Private | F424: 2017 | G424: 2024 | H424: ='mpi_dataset_summary_2017-2024'!$G424-'mpi_dataset_summary_2017-2024'!$F424+1 -> 8 | I424: Under Construction | J424: Under Construction | K424: =IF('mpi_dataset_summary_2017-2024'!$G424=2024,1,0) -> 1 | L424: =IF(J424="Under Construction",1,0) -> 1 | M424: 110 | N424: =_xlfn.PERCENTRANK.INC($M$2:$M$4056,M424) -> 0.372 | O424: 47.553641 | P424: -79.240197 | Q424: Energy | R424: Other | S424: Yes | T424: EN-OTH
A425: 1003 | B425: Churchill Falls (Labrador) Corporation | C425: Electric Utility Capital Expenditures | D425: NL | E425: Private | F425: 2017 | G425: 2023 | H425: ='mpi_dataset_summary_2017-2024'!$G425-'mpi_dataset_summary_2017-2024'!$F425+1 -> 7 | I425: Under Construction | J425: Under Construction | K425: =IF('mpi_dataset_summary_2017-2024'!$G425=2024,1,0) -> 0 | L425: =IF(J425="Under Construction",1,0) -> 1 | M425: 70 | N425: =_xlfn.PERCENTRANK.INC($M$2:$M$4056,M425) -> 0.276 | O425: 53.594608 | P425: -64.308031 | Q425: Energy | R425: Other | S425: Yes | T425: EN-OTH
A426: 1004 | B426: Manitoba Hydro | C426: Manitoba‚ÄìMinnesota Transmission Project | D426: MB | E426: Public | F426: 2017 | G426: 2019 | H426: ='mpi_dataset_summary_2017-2024'!$G426-'mpi_dataset_summary_2017-2024'!$F426+1 -> 3 | I426: In Review | J426: In Review | K426: =IF('mpi_dataset_summary_2017-2024'!$G426=2024,1,0) -> 0 | L426: =IF(J426="Under Construction",1,0) -> 0 | M426: 453 | N426: =_xlfn.PERCENTRANK.INC($M$2:$M$4056,M426) -> 0.664 | O426: 49.988 | P426: -97.43 | Q426: Energy | R426: Trans & Distr | S426: No | T426: EN-T&D
...
